kodexa_cli/__init__.py
kodexa_cli/charts/extension-pack/.helmignore
kodexa_cli/charts/extension-pack/Chart.yaml
kodexa_cli/charts/extension-pack/resources/.gitkeep
kodexa_cli/charts/extension-pack/templates/NOTES.txt
kodexa_cli/charts/extension-pack/templates/_helpers.tpl
kodexa_cli/charts/extension-pack/templates/configmap.yaml
kodexa_cli/charts/extension-pack/values.yaml
kodexa_cli/charts/resource-container/Dockerfile
kodexa_cli/charts/resource-container/health-check.conf
kodexa_cli/charts/resource-container/index.html
kodexa_cli/charts/resource-pack/.helmignore
kodexa_cli/charts/resource-pack/Chart.yaml
kodexa_cli/charts/resource-pack/templates/_helpers.tpl
kodexa_cli/charts/resource-pack/templates/deployment.yaml
kodexa_cli/charts/resource-pack/templates/service.yaml
kodexa_cli/charts/resource-pack/values.yaml
kodexa_cli/cli.py
kodexa_cli/templates/action.jinja2
kodexa_cli/templates/assistant.jinja2
kodexa_cli/templates/content-taxon.jinja2
kodexa_cli/templates/data-store.jinja2
kodexa_cli/templates/document-store.jinja2
kodexa_cli/templates/extension-pack.jinja2
kodexa_cli/templates/header.jinja2
kodexa_cli/templates/index.jinja2
kodexa_cli/templates/model-runtime.jinja2
kodexa_cli/templates/model.jinja2
kodexa_cli/templates/options.jinja2
kodexa_cli/templates/overview.jinja2
kodexa_cli/templates/processing-taxon.jinja2
kodexa_cli/templates/project-template.jinja2
kodexa_cli/templates/store.jinja2
kodexa_cli/templates/taxon.jinja2
kodexa_cli/templates/taxonomy-labels.jinja2
kodexa_cli/templates/taxonomy-structure.jinja2
kodexa_cli/templates/taxonomy.jinja2
kodexa_cli-8.0.14979082538.dist-info/LICENSE
kodexa_cli-8.0.14979082538.dist-info/METADATA
kodexa_cli-8.0.14979082538.dist-info/WHEEL
kodexa_cli-8.0.14979082538.dist-info/entry_points.txt
kodexa_cli-8.0.14979082538.dist-info/RECORD
