Metadata-Version: 2.3
Name: kodexa-cli
Version: 8.0.14979082538
Summary: Command Line Tools for Kodexa
Author: Austin Redenbaugh
Author-email: austin@kodexa.com
Requires-Python: >=3.12,<3.14
Classifier: Programming Language :: Python :: 3
Classifier: Programming Language :: Python :: 3.12
Classifier: Programming Language :: Python :: 3.13
Requires-Dist: PyYAML (>5.0)
Requires-Dist: click (>8.0.0)
Requires-Dist: jinja2 (>=3.1.2,<4.0.0)
Requires-Dist: kodexa (>=8.0.0,<8.1.0)
Requires-Dist: rich (>13.0.0)
Requires-Dist: wrapt (>=1.15.0,<2.0.0)
